{
  "readings": [
    {
      "city": "Mumbai",
      "country": "India",
      "heat_index_celsius": 12.5,
      "humidity_percent": 82.4,
      "latitude": 19.076,
      "longitude": 72.8777,
      "precipitation_mm": 0.0,
      "pressure_hpa": 1008.0,
      "station_id": "STATION_001",
      "temperature_celsius": 12.5,
      "timestamp": "2025-11-02T01:22:58.055102",
      "uv_index": 1,
      "visibility_km": 10.8,
      "weather_condition": "Haze",
      "wind_direction": "N",
      "wind_speed_kmh": 12.8
    },
    {
      "city": "Delhi",
      "country": "India",
      "heat_index_celsius": 14.1,
      "humidity_percent": 71.7,
      "latitude": 28.7041,
      "longitude": 77.1025,
      "precipitation_mm": 8.0,
      "pressure_hpa": 1023.1,
      "station_id": "STATION_002",
      "temperature_celsius": 14.1,
      "timestamp": "2025-11-02T01:22:58.055118",
      "uv_index": 1,
      "visibility_km": 4.3,
      "weather_condition": "Moderate Rain",
      "wind_direction": "E",
      "wind_speed_kmh": 10.3
    },
    {
      "city": "Bangalore",
      "country": "India",
      "heat_index_celsius": 15.3,
      "humidity_percent": 80.0,
      "latitude": 12.9716,
      "longitude": 77.5946,
      "precipitation_mm": 5.9,
      "pressure_hpa": 1020.6,
      "station_id": "STATION_003",
      "temperature_celsius": 15.3,
      "timestamp": "2025-11-02T01:22:58.055143",
      "uv_index": 2,
      "visibility_km": 5.0,
      "weather_condition": "Moderate Rain",
      "wind_direction": "W",
      "wind_speed_kmh": 13.2
    },
    {
      "city": "Chennai",
      "country": "India",
      "heat_index_celsius": 15.9,
      "humidity_percent": 87.6,
      "latitude": 13.0827,
      "longitude": 80.2707,
      "precipitation_mm": 4.0,
      "pressure_hpa": 1015.4,
      "station_id": "STATION_004",
      "temperature_celsius": 15.9,
      "timestamp": "2025-11-02T01:22:58.055154",
      "uv_index": 2,
      "visibility_km": 13.3,
      "weather_condition": "Light Rain",
      "wind_direction": "SE",
      "wind_speed_kmh": 10.2
    },
    {
      "city": "Kolkata",
      "country": "India",
      "heat_index_celsius": 13.7,
      "humidity_percent": 72.7,
      "latitude": 22.5726,
      "longitude": 88.3639,
      "precipitation_mm": 0.0,
      "pressure_hpa": 1011.9,
      "station_id": "STATION_005",
      "temperature_celsius": 13.7,
      "timestamp": "2025-11-02T01:22:58.055164",
      "uv_index": 0,
      "visibility_km": 12.9,
      "weather_condition": "Partly Cloudy",
      "wind_direction": "SW",
      "wind_speed_kmh": 15.6
    }
  ]
}